ruixu_biomcp_test/__init__.py
ruixu_biomcp_test-0.1.0.dist-info/WHEEL
ruixu_biomcp_test-0.1.0.dist-info/entry_points.txt
ruixu_biomcp_test-0.1.0.dist-info/METADATA
ruixu_biomcp_test-0.1.0.dist-info/RECORD
