Metadata-Version: 2.3
Name: ruixu-biomcp-test
Version: 0.1.0
Summary: Add your description here
Author: RuiXu
Author-email: RuiXu <13051109088@163.com>
Requires-Dist: fastmcp>=2.11.3
Requires-Dist: mcp[cli]>=1.13.0
Requires-Python: >=3.13
